minecraft_datapack_language/__init__.py
minecraft_datapack_language/_version.py
minecraft_datapack_language/ast_nodes.py
minecraft_datapack_language/cli.py
minecraft_datapack_language/dir_map.py
minecraft_datapack_language/mdl_compiler.py
minecraft_datapack_language/mdl_errors.py
minecraft_datapack_language/mdl_lexer.py
minecraft_datapack_language/mdl_linter.py
minecraft_datapack_language/mdl_parser.py
minecraft_datapack_language/python_api.py
minecraft_datapack_language/utils.py
minecraft_datapack_language/_embedded/docs/404.html
minecraft_datapack_language/_embedded/docs/Gemfile
minecraft_datapack_language/_embedded/docs/README.md
minecraft_datapack_language/_embedded/docs/_config.yml
minecraft_datapack_language/_embedded/docs/docs.md
minecraft_datapack_language/_embedded/docs/downloads.md
minecraft_datapack_language/_embedded/docs/index.md
minecraft_datapack_language/_embedded/docs/_data/version.yml
minecraft_datapack_language/_embedded/docs/_docs/cli-reference.md
minecraft_datapack_language/_embedded/docs/_docs/contributing.md
minecraft_datapack_language/_embedded/docs/_docs/docs-hub.md
minecraft_datapack_language/_embedded/docs/_docs/documentation.md
minecraft_datapack_language/_embedded/docs/_docs/examples.md
minecraft_datapack_language/_embedded/docs/_docs/getting-started.md
minecraft_datapack_language/_embedded/docs/_docs/language-reference.md
minecraft_datapack_language/_embedded/docs/_docs/multi-file-projects.md
minecraft_datapack_language/_embedded/docs/_docs/python-bindings.md
minecraft_datapack_language/_embedded/docs/_docs/vscode-extension.md
minecraft_datapack_language/_embedded/docs/_includes/head-custom.html
minecraft_datapack_language/_embedded/docs/_includes/navigation.html
minecraft_datapack_language/_embedded/docs/_layouts/default.html
minecraft_datapack_language/_embedded/docs/_layouts/page.html
minecraft_datapack_language/_embedded/docs/_plugins/test_version.rb
minecraft_datapack_language/_embedded/docs/_plugins/version_reader.rb
minecraft_datapack_language-18.0.3.dist-info/licenses/LICENSE
minecraft_datapack_language-18.0.3.dist-info/METADATA
minecraft_datapack_language-18.0.3.dist-info/WHEEL
minecraft_datapack_language-18.0.3.dist-info/entry_points.txt
minecraft_datapack_language-18.0.3.dist-info/top_level.txt
minecraft_datapack_language-18.0.3.dist-info/RECORD
