Metadata-Version: 2.4
Name: minecraft-datapack-language
Version: 18.0.3
Summary: Compile MDL language with explicit scoping into a Minecraft datapack (1.21+ ready). Features variables, control flow, error handling, and VS Code extension.
Project-URL: Homepage, https://www.mcmdl.com
Project-URL: Documentation, https://www.mcmdl.com/docs
Project-URL: Repository, https://github.com/aaron777collins/MinecraftDatapackLanguage
Project-URL: Bug Tracker, https://github.com/aaron777collins/MinecraftDatapackLanguage/issues
Project-URL: VS Code Extension, https://marketplace.visualstudio.com/items?itemName=mdl.minecraft-datapack-language
Classifier: Programming Language :: Python :: 3
Classifier: License :: OSI Approved :: MIT License
Classifier: Operating System :: OS Independent
Requires-Python: >=3.9
License-File: LICENSE
Requires-Dist: mecha>=0.99.0
Provides-Extra: dev
Requires-Dist: pytest>=7.0.0; extra == "dev"
Requires-Dist: pytest-cov>=4.0.0; extra == "dev"
Dynamic: license-file
